Metadata-Version: 2.1
Name: hptdx
Version: 1.20220218
Summary: hpformula for lyy
Author: lyy
Author-email: 
License: MIT
License-File: LICENSE
